README
python-minihallib.spec
setup.cfg
setup.py
examples/hvm
examples/lspci
minihallib/HALDevice.py
minihallib/HALEventerThread.py
minihallib/HALHandler.py
minihallib/HALManager.py
minihallib/HALPlugin.py
minihallib/HALWrapper.py
minihallib/ListBus.py
minihallib/Log.py
minihallib/__init__.py
minihallib.egg-info/PKG-INFO
minihallib.egg-info/SOURCES.txt
minihallib.egg-info/dependency_links.txt
minihallib.egg-info/top_level.txt