Metadata-Version: 1.0
Name: minihallib
Version: 0.1.10
Summary: Library to handle HAL devices and events
Home-page: http://www.smile.org.ua/trac/minihallib
Author: Andy Shevchenko
Author-email: andy@smile.org.ua
License: GPLv2+ or AFL
Keywords: python dbus hal
Platform: Python 2.4 and later
Classifier: Development Status :: 4 - Beta
Classifier: Operating System :: Unix
Classifier: License :: OSI Approved :: Academic Free License (AFL)
Classifier: License :: OSI Approved :: GNU General Public License (GPL)
Classifier: Intended Audience :: Developers
Classifier: Programming Language :: Python
Classifier: Topic :: Software Development :: Libraries :: Python Modules
Classifier: Topic :: System :: Hardware
